glucklabutils/__init__.py
glucklabutils/autoscore.py
glucklabutils/subjectid_to_seqid.py
glucklabutils/autoscore/__init__.py
glucklabutils/autoscore/autoscore.py
glucklabutils/subjectid_to_seqid/__init__.py
glucklabutils/subjectid_to_seqid/subjectid_to_seqid.py
glucklabutils-0.0.4.dist-info/LICENSE
glucklabutils-0.0.4.dist-info/METADATA
glucklabutils-0.0.4.dist-info/WHEEL
glucklabutils-0.0.4.dist-info/top_level.txt
glucklabutils-0.0.4.dist-info/RECORD
