Metadata-Version: 2.1
Name: glucklabutils
Version: 0.0.4
Summary: GluckLab utils
Author: Jose Mojica Perez
Author-email: jlmojicaperez@gmail.com
Keywords: python
Classifier: Development Status :: 3 - Alpha
Classifier: Programming Language :: Python :: 3
Classifier: Operating System :: MacOS :: MacOS X
Classifier: Operating System :: Microsoft :: Windows
License-File: LICENSE
Requires-Dist: pandas
